{
  "id": "n2_062",
  "pattern": "〜を機に",
  "meaning": "taking the opportunity of / on the occasion of (positive catalyst, formal)",
  "level": "N2",
  "exercises": [
    {
      "id": "n2_062_1",
      "example_sentence": "新しい館長の就任を機に、方針が大きく変わった。",
      "translation": "With the new director's appointment, policies changed significantly.",
      "blank_target": "を機に",
      "wrong_choices": [
        "をきっかけに",
        "を契機に",
        "の際に"
      ],
      "wrong_choice_explanations": [
        "をきっかけに is less formal and can be used for both positive and negative triggers, but this formal context requires を機に.",
        "を契機に is very similar but slightly more formal and literary than を機に, making を機に more appropriate here.",
        "の際に means 'at the time of' but lacks the nuance of actively seizing an opportunity that を機に provides."
      ]
    },
    {
      "id": "n2_062_2",
      "example_sentence": "退職を機に、長年の夢だった世界旅行に出かけた。",
      "translation": "Taking the opportunity of retirement, I set out on the long-awaited world trip.",
      "blank_target": "を機に",
      "wrong_choices": [
        "をきっかけに",
        "と同時に",
        "にあたって"
      ],
      "wrong_choice_explanations": [
        "をきっかけに is more casual and doesn't emphasize the positive opportunity aspect as strongly as を機に does.",
        "と同時に simply means 'at the same time' but doesn't capture the sense of seizing an opportunity.",
        "にあたって means 'on the occasion of' but is used more for preparations before events rather than seizing opportunities."
      ]
    },
    {
      "id": "n2_062_3",
      "example_sentence": "バルセロナオリンピックを機に、スペインの観光業が急速に発展した。",
      "translation": "Taking the opportunity of the Barcelona Olympics, Spain's tourism industry developed rapidly.",
      "blank_target": "を機に",
      "wrong_choices": [
        "によって",
        "のおかげで",
        "を通じて"
      ],
      "wrong_choice_explanations": [
        "によって indicates direct causation but doesn't convey the sense of actively seizing an opportunity that を機に expresses.",
        "のおかげで expresses gratitude for a benefit but lacks the formal tone and opportunity-seizing nuance of を機に.",
        "を通じて means 'through' or 'via' but doesn't emphasize the turning point aspect that を機に provides."
      ]
    },
    {
      "id": "n2_062_4",
      "example_sentence": "新システムの導入を機に、業務効率が大幅に改善された。",
      "translation": "Taking the opportunity of introducing the new system, work efficiency was significantly improved.",
      "blank_target": "を機に",
      "wrong_choices": [
        "を境に",
        "に伴って",
        "の結果"
      ],
      "wrong_choice_explanations": [
        "を境に means 'as a boundary/turning point' but doesn't emphasize the positive opportunity aspect as を機に does.",
        "に伴って means 'accompanying' or 'along with' but lacks the sense of actively seizing an opportunity.",
        "の結果 means 'as a result of' but indicates passive consequence rather than actively taking advantage of an opportunity."
      ]
    },
    {
      "id": "n2_062_5",
      "example_sentence": "息子の大学入学を機に、家族で引っ越しを決めた。",
      "translation": "Taking the opportunity of our son's university entrance, we decided to move as a family.",
      "blank_target": "を機に",
      "wrong_choices": [
        "をきっかけに",
        "にちなんで",
        "に合わせて"
      ],
      "wrong_choice_explanations": [
        "をきっかけに is less formal and doesn't emphasize the positive catalyst aspect as strongly as を機に.",
        "にちなんで means 'in connection with' or 'named after' but doesn't convey seizing an opportunity.",
        "に合わせて means 'in accordance with' but suggests coordination rather than seizing an opportunity."
      ]
    },
    {
      "id": "n2_062_6",
      "example_sentence": "会社の創立50周年を機に、新たな事業展開を始めた。",
      "translation": "Taking the opportunity of the company's 50th anniversary, we began new business development.",
      "blank_target": "を機に",
      "wrong_choices": [
        "を記念して",
        "を祝って",
        "の際に"
      ],
      "wrong_choice_explanations": [
        "を記念して means 'in commemoration of' but focuses on honoring the past rather than seizing future opportunities.",
        "を祝って means 'in celebration of' but emphasizes the celebratory aspect rather than the opportunity-seizing aspect.",
        "の際に means 'on the occasion of' but lacks the proactive opportunity-seizing nuance of を機に."
      ]
    },
    {
      "id": "n2_062_7",
      "example_sentence": "新技術の開発を機に、市場での競争力が向上した。",
      "translation": "Taking the opportunity of developing new technology, competitiveness in the market improved.",
      "blank_target": "を機に",
      "wrong_choices": [
        "のせいで",
        "を通して",
        "に基づいて"
      ],
      "wrong_choice_explanations": [
        "のせいで indicates blame or negative causation, which contradicts the positive opportunity context of を機に.",
        "を通して means 'through' or 'by means of' but doesn't emphasize the opportunity-seizing aspect.",
        "に基づいて means 'based on' but indicates foundation rather than seizing an opportunity for change."
      ]
    },
    {
      "id": "n2_062_8",
      "example_sentence": "部長への昇進を機に、マネジメント手法を見直した。",
      "translation": "Taking the opportunity of promotion to department manager, I reviewed my management methods.",
      "blank_target": "を機に",
      "wrong_choices": [
        "と共に",
        "について",
        "によると"
      ],
      "wrong_choice_explanations": [
        "と共に means 'together with' but doesn't convey the sense of using something as an opportunity for change.",
        "について means 'about' or 'concerning' but doesn't fit grammatically or meaningfully in this context.",
        "によると means 'according to' but is used for reporting information, not for expressing opportunity-taking."
      ]
    },
    {
      "id": "n2_062_9",
      "example_sentence": "新店舗のオープンを機に、ブランドイメージを刷新した。",
      "translation": "Taking the opportunity of opening a new store, we renewed our brand image.",
      "blank_target": "を機に",
      "wrong_choices": [
        "を中心に",
        "に関して",
        "に対して"
      ],
      "wrong_choice_explanations": [
        "を中心に means 'centered on' but doesn't convey the opportunity-seizing aspect of を機に.",
        "に関して means 'regarding' or 'concerning' but doesn't fit the context of taking advantage of an opportunity.",
        "に対して means 'toward' or 'against' but doesn't express the meaning of seizing an opportunity."
      ]
    },
    {
      "id": "n2_062_10",
      "example_sentence": "結婚を機に、健康的なライフスタイルに変えることにした。",
      "translation": "Taking the opportunity of getting married, I decided to change to a healthy lifestyle.",
      "blank_target": "を機に",
      "wrong_choices": [
        "のために",
        "について",
        "に向けて"
      ],
      "wrong_choice_explanations": [
        "のために means 'for the purpose of' but indicates doing something for someone/something rather than seizing an opportunity.",
        "について means 'about' or 'concerning' but doesn't grammatically fit or convey the opportunity-taking meaning.",
        "に向けて means 'toward' or 'heading for' but indicates direction rather than using something as a catalyst for change."
      ]
    }
  ]
}
