{
  "id": "n4_078",
  "pattern": "～わけにはいかない",
  "meaning": "Cannot very well do ~; cannot bring oneself to do ~",
  "level": "N4",
  "exercises": [
    {
      "id": "n4_078_1",
      "example_sentence": "約束したのだから、行かない__にはいかない。",
      "translation": "Since I promised, I can't very well not go.",
      "blank_target": "わけ",
      "wrong_choices": [
        "つもり",
        "はず",
        "べき"
      ],
      "wrong_choice_explanations": [
        "つもり means 'intention' — it expresses personal intention rather than social obligation that わけにはいかない conveys.",
        "はず means 'should be' or 'expected' — it expresses expectation rather than the social constraint of わけにはいかない.",
        "べき means 'should' or 'ought to' — while expressing obligation, it's direct moral duty rather than social impossibility."
      ]
    },
    {
      "id": "n4_078_2",
      "example_sentence": "他の人が働いているのに、私だけ休む__にはいかない。",
      "translation": "While others are working, I can't very well rest alone.",
      "blank_target": "わけ",
      "wrong_choices": [
        "もの",
        "こと",
        "の"
      ],
      "wrong_choice_explanations": [
        "もの creates emphasis or explanation — it doesn't express the social constraint that わけにはいかない provides.",
        "こと nominalizes the verb — it doesn't create the meaning of social impossibility that this context requires.",
        "の is a nominalizing particle — it doesn't convey the sense of social obligation or constraint."
      ]
    },
    {
      "id": "n4_078_3",
      "example_sentence": "お客様の前で、そんなことを言う__にはいかません。",
      "translation": "I can't very well say such things in front of customers.",
      "blank_target": "わけ",
      "wrong_choices": [
        "ため",
        "ので",
        "から"
      ],
      "wrong_choice_explanations": [
        "ため means 'for' or 'because of' — it shows purpose or reason rather than social impossibility.",
        "ので means 'because' — it expresses causation rather than the social constraint of わけにはいかない.",
        "から means 'because' — it shows reason or cause, not the social obligation or impossibility."
      ]
    },
    {
      "id": "n4_078_4",
      "example_sentence": "彼に嘘をついた以上、謝らない__にはいかない。",
      "translation": "Since I lied to him, I can't very well not apologize.",
      "blank_target": "わけ",
      "wrong_choices": [
        "ところ",
        "まま",
        "ばかり"
      ],
      "wrong_choice_explanations": [
        "ところ means 'place' or 'point' — it doesn't create the meaning of social obligation that わけにはいかない expresses.",
        "まま means 'as is' or 'remaining' — it shows unchanged state rather than social impossibility.",
        "ばかり means 'only' or 'just' — it shows limitation rather than the social constraint meaning needed here."
      ]
    },
    {
      "id": "n4_078_5",
      "example_sentence": "みんなが頑張っているのに、私だけサボる__にはいかない。",
      "translation": "While everyone is working hard, I can't very well slack off alone.",
      "blank_target": "わけ",
      "wrong_choices": [
        "ほど",
        "だけ",
        "しか"
      ],
      "wrong_choice_explanations": [
        "ほど means 'extent' or 'degree' — it shows degree rather than the social impossibility that わけにはいかない expresses.",
        "だけ means 'only' — it shows limitation but doesn't create the social constraint meaning.",
        "しか means 'only' (with negative) — it expresses limitation rather than social obligation or impossibility."
      ]
    },
    {
      "id": "n4_078_6",
      "example_sentence": "借りたお金を返さない__にはいかない。",
      "translation": "I can't very well not return the money I borrowed.",
      "blank_target": "わけ",
      "wrong_choices": [
        "限り",
        "以上",
        "うちに"
      ],
      "wrong_choice_explanations": [
        "限り means 'as long as' — it creates conditional meaning rather than expressing social obligation.",
        "以上 means 'since' or 'now that' — it shows reasoning from a fact rather than social impossibility.",
        "うちに means 'while' — it indicates time period rather than the social constraint of わけにはいかない."
      ]
    },
    {
      "id": "n4_078_7",
      "example_sentence": "会社の規則だから、守らない__にはいかない。",
      "translation": "Since it's a company rule, I can't very well not follow it.",
      "blank_target": "わけ",
      "wrong_choices": [
        "せい",
        "おかげ",
        "かぎり"
      ],
      "wrong_choice_explanations": [
        "せい means 'fault' or 'because of' (negative) — it assigns blame rather than expressing social obligation.",
        "おかげ means 'thanks to' — it expresses gratitude rather than the social constraint of わけにはいかない.",
        "かぎり means 'as long as' — it shows conditions or limits rather than social impossibility."
      ]
    },
    {
      "id": "n4_078_8",
      "example_sentence": "親に心配をかける__にはいかない。",
      "translation": "I can't very well worry my parents.",
      "blank_target": "わけ",
      "wrong_choices": [
        "ように",
        "ことに",
        "つもりで"
      ],
      "wrong_choice_explanations": [
        "ように means 'so that' or 'in order to' — it expresses purpose rather than social impossibility.",
        "ことに means 'deciding to' — it expresses decision rather than the social constraint of わけにはいかない.",
        "つもりで means 'with the intention of' — it expresses intention rather than social obligation or impossibility."
      ]
    },
    {
      "id": "n4_078_9",
      "example_sentence": "先生の前で、携帯電話を使う__にはいかない。",
      "translation": "I can't very well use my phone in front of the teacher.",
      "blank_target": "わけ",
      "wrong_choices": [
        "ようだ",
        "そうだ",
        "らしい"
      ],
      "wrong_choice_explanations": [
        "ようだ means 'seems like' — it expresses appearance or resemblance rather than social constraint.",
        "そうだ means 'seems' or 'I heard' — it expresses appearance or hearsay rather than social impossibility.",
        "らしい means 'seems like' — it expresses appearance or hearsay rather than the social obligation meaning."
      ]
    },
    {
      "id": "n4_078_10",
      "example_sentence": "チームの一員として、責任を放棄する__にはいかない。",
      "translation": "As a team member, I can't very well abandon my responsibilities.",
      "blank_target": "わけ",
      "wrong_choices": [
        "かもしれない",
        "に違いない",
        "だろう"
      ],
      "wrong_choice_explanations": [
        "かもしれない means 'might' or 'maybe' — it expresses possibility rather than social constraint.",
        "に違いない means 'must be' — it expresses strong certainty rather than the social impossibility of わけにはいかない.",
        "だろう means 'probably' — it expresses probability rather than the social obligation or constraint meaning."
      ]
    }
  ]
}
