{
  "id": "n2_178",
  "pattern": "〜面で",
  "meaning": "in terms of / on the side of (an aspect or dimension)",
  "level": "N2",
  "exercises": [
    {
      "id": "n2_178_1",
      "example_sentence": "経済面で、課題が多く残っている。",
      "translation": "In terms of economics, many challenges remain.",
      "blank_target": "面で",
      "wrong_choices": [
        "点で",
        "によって",
        "のため"
      ],
      "wrong_choice_explanations": [
        "〜点で highlights one specific point or respect and normally pairs with その/という (e.g. その点で, 〜という点で); it doesn't attach to a bare domain noun the way 面で does to mark a whole aspect like 'the economic side.'",
        "〜によって means 'depending on' or 'by means of'; 経済によって would make the economy the cause or variable, not the dimension being discussed, which is 面で's job.",
        "〜のため means 'for the sake of' or 'because of'; it marks purpose or cause, not the aspect ('the economic side') that 面で picks out."
      ],
      "hiragana_full": "けいざいめんで、かだいがおおくのこっている。",
      "audio_alternatives": [
        {
          "kanji": "経済的に、多くの課題が残っている。",
          "hiragana_full": "けいざいてきに、おおくのかだいがのこっている。"
        },
        {
          "kanji": "経済の面では、課題がたくさん残っている。",
          "hiragana_full": "けいざいのめんでは、かだいがたくさんのこっている。"
        }
      ],
      "audio_eligible": true
    },
    {
      "id": "n2_178_2",
      "example_sentence": "社会面で、大きな変化が起こっている。",
      "translation": "In terms of society, major changes are occurring.",
      "blank_target": "面で",
      "wrong_choices": [
        "という点で",
        "次第で",
        "として"
      ],
      "wrong_choice_explanations": [
        "〜という点で means 'in the respect that ~' and characterizes something by a particular feature; 社会という点で ('in the respect that it is society') doesn't fit, whereas 面で simply names the social dimension.",
        "〜次第で means 'depending on'; 社会次第で would make society a deciding variable, not the dimension in which the changes occur, which is what 面で marks.",
        "〜として means 'as / in the capacity of'; 社会として ('as a society') assigns a role, not the aspect being discussed that 面で expresses."
      ],
      "hiragana_full": "しゃかいめんで、おおきなへんかがおこっている。",
      "audio_alternatives": [
        {
          "kanji": "社会的に、大きな変化が生じている。",
          "hiragana_full": "しゃかいてきに、おおきなへんかがしょうじている。"
        },
        {
          "kanji": "社会の面では、大きな変化が起きている。",
          "hiragana_full": "しゃかいのめんでは、おおきなへんかがおきている。"
        }
      ],
      "audio_eligible": true
    },
    {
      "id": "n2_178_3",
      "example_sentence": "技術面で、ライバル企業に遅れている。",
      "translation": "In terms of technology, we are behind rival companies.",
      "blank_target": "面で",
      "wrong_choices": [
        "について",
        "の観点から",
        "に基づいて"
      ],
      "wrong_choice_explanations": [
        "〜について means 'about / concerning' a topic of discussion; it pairs with verbs like 話す or 考える, and 技術について遅れている reads oddly, whereas 面で marks the technical dimension of falling behind.",
        "〜の観点から means 'from the viewpoint of' and frames a perspective one takes; 面で instead points to the dimension itself (the technical side) rather than a vantage point.",
        "〜に基づいて means 'based on / on the basis of'; 技術に基づいて would make technology the grounds for an action, not the aspect in which the company lags, which 面で conveys."
      ],
      "hiragana_full": "ぎじゅつめんで、らいばるきぎょうにおくれている。",
      "audio_alternatives": [
        {
          "kanji": "技術的に、ライバル企業より遅れをとっている。",
          "hiragana_full": "ぎじゅつてきに、らいばるきぎょうよりおくれをとっている。"
        },
        {
          "kanji": "技術の面では、ライバル企業に後れを取っている。",
          "hiragana_full": "ぎじゅつのめんでは、らいばるきぎょうにおくれをとっている。"
        }
      ],
      "audio_eligible": true
    },
    {
      "id": "n2_178_4",
      "example_sentence": "人材面で、採用が困難になっている。",
      "translation": "In terms of personnel, recruitment is becoming difficult.",
      "blank_target": "面で",
      "wrong_choices": [
        "にとって",
        "として",
        "の分野で"
      ],
      "wrong_choice_explanations": [
        "〜にとって means 'for/to someone' and indicates who is affected, not which aspect is being discussed.",
        "〜として means 'as' and indicates role or capacity, not the aspect being considered.",
        "〜の分野で means 'in the field of' and focuses on professional areas rather than aspects or dimensions."
      ],
      "hiragana_full": "じんざいめんで、さいようがこんなんになっている。",
      "audio_alternatives": [
        {
          "kanji": "人材の面では、採用が難しくなっている。",
          "hiragana_full": "じんざいのめんでは、さいようがむずかしくなっている。"
        },
        {
          "kanji": "人材確保の観点から、採用が困難になっている。",
          "hiragana_full": "じんざいかくほのかんてんから、さいようがこんなんになっている。"
        }
      ],
      "audio_eligible": true
    },
    {
      "id": "n2_178_5",
      "example_sentence": "環境面で、対策が急務だ。",
      "translation": "In terms of environment, countermeasures are urgent.",
      "blank_target": "面で",
      "wrong_choices": [
        "問題で",
        "のことで",
        "によって"
      ],
      "wrong_choice_explanations": [
        "〜問題で reads as 'due to the ~ problem' and turns 環境問題 into a cause; that changes the meaning, whereas 面で marks the environmental dimension in which action is urgent.",
        "〜のことで means 'about the matter of'; it points to a specific issue under discussion, not the broad aspect ('the environmental side') that 面で picks out.",
        "〜によって means 'depending on / by means of'; 環境によって would treat the environment as a cause or variable, not the dimension being addressed, which is 面で's role."
      ],
      "hiragana_full": "かんきょうめんで、たいさくがきゅうむだ。",
      "audio_alternatives": [
        {
          "kanji": "環境面において、対策が急務です。",
          "hiragana_full": "かんきょうめんにおいて、たいさくがきゅうむです。"
        },
        {
          "kanji": "環境の面から見て、対策が急がれる。",
          "hiragana_full": "かんきょうのめんからみて、たいさくがいそがれる。"
        }
      ],
      "audio_eligible": true
    },
    {
      "id": "n2_178_6",
      "example_sentence": "安全面で、改善が必要だ。",
      "translation": "In terms of safety, improvements are necessary.",
      "blank_target": "面で",
      "wrong_choices": [
        "の件で",
        "に対して",
        "場面で"
      ],
      "wrong_choice_explanations": [
        "〜の件で means 'regarding the matter of' and is used for specific cases or incidents, not aspects.",
        "〜に対して means 'toward/against' and indicates direction or target, not the aspect being discussed.",
        "〜場面で means 'in the situation of' and refers to specific scenarios, not broad aspects or dimensions."
      ],
      "hiragana_full": "あんぜんめんで、かいぜんがひつようだ。",
      "audio_alternatives": [
        {
          "kanji": "安全面において、改善が必要だ。",
          "hiragana_full": "あんぜんめんにおいて、かいぜんがひつようだ。"
        },
        {
          "kanji": "安全性の面で、改善が必要です。",
          "hiragana_full": "あんぜんせいのめんで、かいぜんがひつようです。"
        }
      ],
      "audio_eligible": true
    },
    {
      "id": "n2_178_7",
      "example_sentence": "健康面で、注意が必要です。",
      "translation": "In terms of health, caution is necessary.",
      "blank_target": "面で",
      "wrong_choices": [
        "関連で",
        "方面で",
        "のため"
      ],
      "wrong_choice_explanations": [
        "〜関連で means 'in connection with' and emphasizes relationships rather than aspects or dimensions.",
        "〜方面で means 'in the direction of' and refers to geographical or organizational directions, not aspects.",
        "〜のため means 'for the sake of' and indicates purpose or reason, not the aspect being discussed."
      ],
      "hiragana_full": "けんこうめんで、ちゅういがひつようです。",
      "audio_alternatives": [
        {
          "kanji": "健康面において、注意が必要です。",
          "hiragana_full": "けんこうめんにおいて、ちゅういがひつようです。"
        },
        {
          "kanji": "健康に関して、注意が必要です。",
          "hiragana_full": "けんこうにかんして、ちゅういがひつようです。"
        }
      ],
      "audio_eligible": true
    },
    {
      "id": "n2_178_8",
      "example_sentence": "コスト面で、削減が求められている。",
      "translation": "In terms of cost, reduction is being demanded.",
      "blank_target": "面で",
      "wrong_choices": [
        "部分で",
        "方向で",
        "なので"
      ],
      "wrong_choice_explanations": [
        "〜部分で means 'in the part of' and refers to physical or specific portions, not aspects or dimensions.",
        "〜方向で means 'in the direction of' and indicates directional movement, not aspects being considered.",
        "〜なので means 'because of' and indicates reason or cause, completely changing the sentence structure."
      ],
      "hiragana_full": "こすとめんで、さくげんがもとめられている。",
      "audio_alternatives": [
        {
          "kanji": "コスト面において、削減が求められている。",
          "hiragana_full": "こすとめんにおいて、さくげんがもとめられている。"
        },
        {
          "kanji": "費用の面で、削減が求められている。",
          "hiragana_full": "ひようのめんで、さくげんがもとめられている。"
        }
      ],
      "audio_eligible": true
    },
    {
      "id": "n2_178_9",
      "example_sentence": "品質面で、競合他社に負けていない。",
      "translation": "In terms of quality, we are not losing to competitors.",
      "blank_target": "面で",
      "wrong_choices": [
        "に比べて",
        "のせいで",
        "次第で"
      ],
      "wrong_choice_explanations": [
        "〜に比べて means 'compared to' and sets up a direct comparison; 品質に比べて would compare against quality itself, whereas 面で marks quality as the dimension in which the company holds its own.",
        "〜のせいで assigns blame ('because of'); it makes quality a negative cause, not the aspect being evaluated that 面で conveys.",
        "〜次第で means 'depending on'; 品質次第で would make quality a deciding variable, not the dimension in which the firm is not losing, which is what 面で marks."
      ],
      "hiragana_full": "ひんしつめんで、きょうごうたしゃにまけていない。",
      "audio_alternatives": [
        {
          "kanji": "品質の面では、競合他社に引けを取らない。",
          "hiragana_full": "ひんしつのめんでは、きょうごうたしゃにひけをとらない。"
        },
        {
          "kanji": "品質において、競合他社に劣っていない。",
          "hiragana_full": "ひんしつにおいて、きょうごうたしゃにおとっていない。"
        }
      ],
      "audio_eligible": true
    },
    {
      "id": "n2_178_10",
      "example_sentence": "教育面で、地域格差が問題となっている。",
      "translation": "In terms of education, regional disparities are becoming a problem.",
      "blank_target": "面で",
      "wrong_choices": [
        "領域で",
        "関係で",
        "のもとで"
      ],
      "wrong_choice_explanations": [
        "〜領域で means 'in the domain of' and refers to territories or fields, but lacks the aspect nuance of 〜面で.",
        "〜関係で means 'in relation to' and emphasizes connections or relationships rather than aspects or dimensions.",
        "〜のもとで means 'under the influence/guidance of' and indicates control or supervision, not aspects being discussed."
      ],
      "hiragana_full": "きょういくめんで、ちいきかくさがもんだいとなっている。",
      "audio_alternatives": [
        {
          "kanji": "教育の面では、地域格差が問題になっている。",
          "hiragana_full": "きょういくのめんでは、ちいきかくさがもんだいになっている。"
        },
        {
          "kanji": "教育における地域格差が問題となっている。",
          "hiragana_full": "きょういくにおけるちいきかくさがもんだいとなっている。"
        }
      ],
      "audio_eligible": true
    }
  ]
}
